Metadata-Version: 2.3
Name: mcp-server-dongjun
Version: 0.1.0
Summary: Add your description here
Author: DongJun
Author-email: DongJun <you@example.com>
Requires-Dist: mcp[cli]>=1.12.3
Requires-Python: >=3.11
